readme.rst
vibration_toolbox/__init__.py
vibration_toolbox/conftest.py
vibration_toolbox/continuous_systems.py
vibration_toolbox/ema.py
vibration_toolbox/mdof.py
vibration_toolbox/readme.rst
vibration_toolbox/sdof.py
vibration_toolbox/vibesystem.py
vibration_toolbox/data/case1.mat
vibration_toolbox/data/case2.mat
vibration_toolbox/data/frf_data1.mat
vibration_toolbox-0.6.10.dist-info/LICENSE.txt
vibration_toolbox-0.6.10.dist-info/METADATA
vibration_toolbox-0.6.10.dist-info/WHEEL
vibration_toolbox-0.6.10.dist-info/top_level.txt
vibration_toolbox-0.6.10.dist-info/RECORD
