Metadata-Version: 2.1
Name: vibration-toolbox
Version: 0.6.10
Summary: Educational code illustrating fundamentals of vibration                    for engineers.
Home-page: https://github.com/vibrationtoolbox/vibration_toolbox
Author: Joseph C. Slater and Raphael Timbó
Author-email: joseph.c.slater@gmail.com
License: UNKNOWN
Keywords: vibration,mechanical engineering,civil engineering
Platform: UNKNOWN
Requires-Dist: numpy
Requires-Dist: scipy
Requires-Dist: matplotlib
Requires-Dist: jupyter
